compflow/__init__.py
compflow/compflow.py
compflow-0.1.0.dist-info/LICENSE
compflow-0.1.0.dist-info/METADATA
compflow-0.1.0.dist-info/WHEEL
compflow-0.1.0.dist-info/top_level.txt
compflow-0.1.0.dist-info/RECORD
