Metadata-Version: 2.1
Name: compflow
Version: 0.1.0
Summary: Compressible flow tables
Home-page: https://github.com/jb753/compflow
Author: James Brind
Author-email: brind.james@gmail.com
License: UNKNOWN
Platform: UNKNOWN
Classifier: Programming Language :: Python :: 3
Classifier: License :: OSI Approved :: MIT License
Classifier: Operating System :: OS Independent
Requires-Python: >=3.7
Requires-Dist: numpy
Requires-Dist: scipy
